abdullahfunctions/__init__.py
abdullahfunctions/abdullahfunctions.py
abdullahfunctions-0.0.1.dist-info/METADATA
abdullahfunctions-0.0.1.dist-info/WHEEL
abdullahfunctions-0.0.1.dist-info/top_level.txt
abdullahfunctions-0.0.1.dist-info/RECORD
