Metadata-Version: 2.1
Name: abdullahfunctions
Version: 0.0.1
Summary: An example python package
Home-page: UNKNOWN
Author: Abdullah Tatlisumak
Author-email: matatlisumak@gmail.com
License: MIT
Platform: UNKNOWN
Classifier: Programming Language :: Python :: 3
Classifier: License :: OSI Approved :: MIT License
Classifier: Operating System :: OS Independent
Requires-Dist: numpy
